sms_plusserver.py
sms_plusserver-1.0.0.dist-info/LICENSE
sms_plusserver-1.0.0.dist-info/METADATA
sms_plusserver-1.0.0.dist-info/WHEEL
sms_plusserver-1.0.0.dist-info/top_level.txt
sms_plusserver-1.0.0.dist-info/RECORD
