Metadata-Version: 2.1
Name: sms-plusserver
Version: 1.0.0
Summary: Python library that allows to send messages using Plusserver SMS platform.
Home-page: https://github.com/W-Z-FinTech-GmbH/sms_plusserver
Author: W&Z FinTech GmbH
Author-email: dk@ownly.de
License: MIT
Keywords: s,m,s, ,p,l,u,s,s,e,r,v,e,r, ,m,e,s,s,a,g,e, ,t,e,x,t, ,p,h,o,n,e
Platform: UNKNOWN
Classifier: Development Status :: 4 - Beta
Classifier: Intended Audience :: Developers
Classifier: License :: OSI Approved :: MIT License
Classifier: Operating System :: OS Independent
Classifier: Programming Language :: Python :: 2
Classifier: Programming Language :: Python :: 2.7
Classifier: Programming Language :: Python :: 3
Classifier: Programming Language :: Python :: 3.5
Classifier: Topic :: Utilities
Requires-Dist: requests (>=2.1)
Requires-Dist: six
